osunbit/__init__.py
osunbit-0.0.1.dist-info/METADATA
osunbit-0.0.1.dist-info/WHEEL
osunbit-0.0.1.dist-info/top_level.txt
osunbit-0.0.1.dist-info/RECORD
