Metadata-Version: 2.4
Name: osunbit
Version: 0.0.1
Summary: Basic Osunbit SDK for Python
Author: Your Name
Classifier: Programming Language :: Python :: 3
Requires-Python: >=3.6
Dynamic: author
Dynamic: classifier
Dynamic: description
Dynamic: description-content-type
Dynamic: requires-python
Dynamic: summary
